{"value": {"source": "PSA OpenStat (Sample Data)", "province": "Pangasinan", "year": 2024, "quarter": null, "data": {"area_harvested": {"value": 185420, "unit": "hectares", "description": "Total area harvested for palay"}, "production": {"value": 892150, "unit": "metric tons", "description": "Total production output"}, "average_price": {"value": 22.5, "unit": "PHP/kg", "description": "Average palay price"}}, "timestamp": "2025-11-17T12:51:08.701377", "note": "Sample data - for real data visit https://openstat.psa.gov.ph"}, "created_at": "2025-11-17T04:51:08.701377"}